{
  "schema": 2,
  "last_updated": "2026-07-06T19:57:57.090196+00:00",
  "disclaimer": "Educational market context — not financial advice.",
  "topics": [
    "markets",
    "nasdaq",
    "s&p 500",
    "crypto",
    "forex",
    "gold",
    "oil"
  ],
  "aliases": {
    "btc": "crypto",
    "bitcoin": "crypto",
    "btc/usd": "crypto",
    "btcusd": "crypto",
    "eth": "crypto",
    "ethereum": "crypto",
    "eth/usd": "crypto",
    "ethusd": "crypto",
    "sol": "crypto",
    "solana": "crypto",
    "xrp": "crypto",
    "ripple": "crypto",
    "altcoins": "crypto",
    "crypto market": "crypto",
    "ndx": "nasdaq",
    "us100": "nasdaq",
    "nas100": "nasdaq",
    "nas 100": "nasdaq",
    "nasdaq 100": "nasdaq",
    "nasdaq100": "nasdaq",
    "nq": "nasdaq",
    "qqq": "nasdaq",
    "tech": "nasdaq",
    "spx": "s&p 500",
    "sp500": "s&p 500",
    "sp 500": "s&p 500",
    "s&p": "s&p 500",
    "s&p500": "s&p 500",
    "es": "s&p 500",
    "us500": "s&p 500",
    "spx500": "s&p 500",
    "spy": "s&p 500",
    "us30": "markets",
    "dow": "markets",
    "dow jones": "markets",
    "djia": "markets",
    "ym": "markets",
    "us 30": "markets",
    "indices": "markets",
    "stocks": "markets",
    "equities": "markets",
    "xau": "gold",
    "xauusd": "gold",
    "xau/usd": "gold",
    "gold spot": "gold",
    "gold price": "gold",
    "wti": "oil",
    "crude": "oil",
    "crude oil": "oil",
    "usoil": "oil",
    "us oil": "oil",
    "brent": "oil",
    "cl": "oil",
    "fx": "forex",
    "dxy": "forex",
    "dollar": "forex",
    "dollar index": "forex",
    "eurusd": "forex",
    "eur/usd": "forex",
    "eur usd": "forex",
    "gbpusd": "forex",
    "gbp/usd": "forex",
    "gbp usd": "forex",
    "cable": "forex",
    "usdjpy": "forex",
    "usd/jpy": "forex",
    "gbpjpy": "forex",
    "gbp/jpy": "forex",
    "audusd": "forex",
    "aud/usd": "forex",
    "usdcad": "forex",
    "usd/cad": "forex",
    "nzdusd": "forex",
    "nzd/usd": "forex"
  },
  "ai_summaries": {
    "markets": "The market is currently experiencing a modest uptick, reflecting a sense of stabilization as the New York PM killzone unfolds. Price has remained broadly rangebound since the Asia session, coiling tightly within a premium zone. This activity suggests smart money is likely positioning for liquidity opportunities, with recent sweeps of both buyside and sellside liquidity earlier today.\n\n• Nasdaq and S&P 500 are buoyed by a rebound in tech stocks, particularly chips, indicating a shift in market sentiment.\n• The Dow has crossed the psychological 53,000 mark for the first time, highlighting bullish momentum.\n• The overall market is in a premium zone of its current range, with prior-day highs and lows both swept today, signaling potential for further manipulation.\n\nRecent headlines emphasize the tech sector's rebound and the overall market's positive trajectory, despite some jitters. As we navigate through this active killzone, traders should watch for how price interacts with key structural levels, particularly the equilibrium around 53,181.\n\nWHAT TO WATCH  \n• Monitor reactions near the swept prior-day high of 53,257 for potential signs of further displacement.  \n• Observe any shifts in market structure that could indicate a new phase of accumulation or distribution, especially following the liquidity-seeking behavior in this session.  \n• Pay attention to the upcoming USD FOMC Meeting Minutes on Wednesday as a catalyst that could introduce volatility.  \n\nSAGE INSIGHT: Today’s market action illustrates the concept of a breaker block. With the prior-day high and low both swept, the current price movement indicates a potential shift in market structure. As price interacts within this premium zone, traders should consider how these breaker blocks can redefine bullish or bearish sentiment, providing insight into future price dynamics as liquidity is sought.",
    "nasdaq": "Today's Nasdaq performance shows a robust upward movement, with price pushing higher and holding near session highs as we enter the active New York PM killzone. This timeframe often sees liquidity sought by smart money, further fueling momentum. \n\n• Price action has been broadly rangebound since the Asia session but has recently shifted higher, indicating a potential market structure shift.\n• The Nasdaq is currently in the premium zone of its working range, reflecting strong bullish sentiment.\n• Notably, the prior-day high was swept, indicating that buy-side liquidity has been targeted successfully.\n\nThe buzz around SpaceX's impending inclusion in the Nasdaq-100 is generating significant interest, with expectations of passive buying driving price action. This inclusion is likely to enhance the bullish narrative, as traders anticipate further movement from ETFs adjusting their holdings.\n\nWith the economic calendar highlighting the USD FOMC Meeting Minutes mid-week, volatility could increase. This event may influence market sentiment and liquidity dynamics.\n\nWHAT TO WATCH  \n• Observe how price reacts near the equilibrium level of 29808 as it continues to test the premium zone.  \n• Watch for any signs of a market structure shift if price breaks below recent lows or continues to sweep higher.  \n• The FOMC Meeting Minutes on Wednesday could act as a catalyst for volatility and liquidity shifts.\n\nSAGE INSIGHT: Displacement is evident as price has moved decisively through both the prior-day high and low, indicating strong buying interest and a shift in market sentiment. This reinforces that smart money is actively engaging in the market, which can lead to further accumulation if the upward momentum continues. Traders should be mindful of how displacement can signal the intent of larger players, often preceding significant movement.",
    "s&p 500": "The S&P 500 is currently pushing higher during the New York PM killzone, maintaining an upward trajectory since the Asia session. Recent action shows price holding near session highs, indicating strong bullish sentiment. As it sits in the premium zone of its current range, with significant liquidity taken from both the prior-day high and low, there's a clear focus on the ongoing flow of capital into equities, particularly driven by tech and AI-related stocks.\n\n• Major indices are buoyed by a rebound in AI-tied stocks, contributing to overall market strength.\n• The recent sweep of buyside liquidity at 7571 confirms the bullish momentum, while the sellside liquidity at 7552 has also been addressed.\n• The flat US Dollar and declining yields are supporting risk-on sentiment, facilitating the upward movement.\n\nWith key economic events on the horizon, including the FOMC Meeting Minutes on Wednesday, traders are likely to remain vigilant for potential volatility catalysts that may influence liquidity dynamics further.\n\nWHAT TO WATCH  \n• Watch for reactions at the upper range of 7602, where selling pressure may emerge.  \n• Monitor any shifts in market structure, particularly if a break below the recent high of 7571 occurs.  \n• Look for volatility around the upcoming FOMC Meeting Minutes on Wednesday, as it could drive liquidity and market sentiment.\n\nSAGE INSIGHT: Today's upward movement in the S&P 500 highlights a liquidity sweep scenario. The aggressive taking of buyside liquidity at prior highs suggests smart money is positioning for further gains, drawing in late participants. This reinforces the concept that liquidity sweeps can often precede sustained moves, emphasizing the importance of monitoring these areas for potential trader reactions.",
    "crypto": "Crypto markets are experiencing a slight uptick as price action continues to push higher in the New York PM killzone, a typical window for smart money to seek liquidity. With the crypto Fear & Greed Index currently at 24, indicating extreme fear, traders are watching closely for potential liquidity raids on late shorts.\n\n• Price has been consistently moving higher since the Asia session and is currently holding near the day's highs.\n• The market is positioned in the premium zone of its current working range, having swept both buyside and sellside liquidity today.\n• Analyst sentiment suggests that a quick move upward is expected for Bitcoin following a shallow correction.\n\nDespite the positive movement, persistent ETF outflows are causing some traders to remain cautious. The upcoming USD FOMC Meeting Minutes on Wednesday will be a key event to monitor, as it could introduce volatility and influence market sentiment.\n\nWHAT TO WATCH  \n• Observe reactions around the prior-day high of 63383, where liquidity was recently swept.  \n• Watch for any market structure shifts, particularly in the context of the ongoing rally and extreme fear sentiment.  \n• The USD FOMC Meeting Minutes on Wednesday may serve as a catalyst for price action, especially for liquidity-seeking moves.  \n\nSAGE INSIGHT: Today’s market dynamics illustrate the turtle soup concept, where traders might be drawn into false setups or corrections before a true move occurs. The recent sweep of both buyside and sellside liquidity suggests that the market could be setting up for a more significant move, potentially catching those positioned against the prevailing trend off guard. This reinforces the importance of being aware of traps set by smart money amid turbulent sentiment.",
    "forex": "The forex market is currently holding a steady stance in the New York PM killzone, with price action remaining largely rangebound since the Asia session. As traders await key liquidity events, the price is coiling within a balanced range, sitting in equilibrium at 1.14384.\n\n• The US Dollar Index is slightly up, reflecting a cautious bullish sentiment amidst geopolitical tensions, particularly in the Middle East.\n• Headlines indicate skepticism regarding the dollar's sustainability, with discussions around major top risks while short-term buy and sell liquidity has been swept today at prior levels.\n• The tight trading range (1.14116–1.14653) suggests a market that is digesting recent developments before making a decisive move.\n\nGiven the upcoming NZD rate statements and the FOMC minutes, traders are likely to observe how these catalysts might trigger liquidity dynamics. \n\nWHAT TO WATCH  \n• Watch for reactions around the equilibrium level of 1.14384 as liquidity may be sought in this zone.  \n• Monitor any shifts in market structure, particularly if price breaks from its current range.  \n• The NZD Official Cash Rate announcement tomorrow could prompt volatility, especially if it diverges from market expectations.  \n\nSAGE INSIGHT: Displacement is key in today's context, as the recent sweeps of both buyside and sellside liquidity indicate a market preparing for a significant move. The tight balance within the range suggests that participants are waiting for a catalyst to trigger a directional shift. Understanding displacement helps traders identify when the market may transition from rangebound behavior to a more aggressive move, providing insight into potential opportunities as the conditions evolve.",
    "gold": "Gold is currently moving higher, showing a recovery off recent lows as the New York PM killzone is underway. Price has been grinding up, reflecting a potential liquidity play as smart money seeks to capitalize on the recent sweeps of both sellside and buyside liquidity earlier in the session.\n\n• The session trend has been under pressure since the Asia session but is now gaining traction as price moves upward.\n• Recent action indicates a push to reclaim equilibrium within the current range, which is defined between 4136 and 4216, with equilibrium at 4176.\n• Notably, the prior-day high of 4214 and low of 4184 have both been swept today, indicating that liquidity has been targeted and taken.\n\nWith the US Dollar Index flat and yields slightly down, the environment appears conducive for gold’s rise, as market participants may look to the upcoming FOMC Meeting Minutes for further guidance on monetary policy, which could induce volatility.\n\nWHAT TO WATCH  \n• Watch for reactions around the recent equilibrium level at 4176, where price could consolidate or shift.  \n• Observe the zones around the swept highs at 4214 and lows at 4184 for signs of further liquidity grabs.  \n• Keep an eye on the FOMC Meeting Minutes on Wednesday for potential impact on market sentiment and liquidity dynamics.\n\nSAGE INSIGHT: Today's upward movement in gold reflects a classic liquidity sweep scenario. The sweeps of both the sellside and buyside earlier today indicate that smart money is actively targeting liquidity, setting the stage for potential price action shifts. Understanding this concept helps traders recognize the importance of liquidity zones and how they can drive market behavior in the short term.",
    "oil": "Oil has maintained a flat trajectory as we enter the New York PM killzone, a period where liquidity is often sought. As price holds near the highs, there's a notable activity around the prior-day high that was swept today, indicating a potential liquidity grab.\n\n• Price has been trading higher since the Asia session, now pushing near the equilibrium of its current range.\n• The recent action has seen price holding around 68.75, with the prior high at 68.78 and the low at 68.22 both swept today.\n• The macro context is supporting this stability, with the US dollar marginally flat and the 10Y yield pulling back.\n\nDespite cautious trade reflected in recent headlines, the market seems to be absorbing the news of OPEC production increases and the geopolitical dynamics surrounding the Strait of Hormuz. This backdrop suggests a balancing act, keeping price dynamics in check while traders remain alert for potential volatility around key events like the upcoming USD FOMC Meeting Minutes.\n\nWHAT TO WATCH  \n• Observe reactions around the equilibrium zone at 68.51, which may indicate strength or weakness.  \n• Monitor for structure shifts if price breaches the recent highs or lows.  \n• The USD FOMC Meeting Minutes on Wednesday could serve as a catalyst for significant volatility.  \n\nSAGE INSIGHT: Today’s market structure reflects a classic Judas swing, where price initially lures traders into false confidence by sweeping the prior-day high before potentially reversing. This teaches us that in periods of heightened liquidity-seeking behavior, being aware of such patterns can protect us from premature bias and help us discern genuine market intentions."
  },
  "updated": {
    "markets": "2026-07-06T19:57:21.549026+00:00",
    "nasdaq": "2026-07-06T19:57:27.803227+00:00",
    "s&p 500": "2026-07-06T19:57:33.424656+00:00",
    "crypto": "2026-07-06T19:57:39.500303+00:00",
    "forex": "2026-07-06T19:57:45.659296+00:00",
    "gold": "2026-07-06T19:57:51.091204+00:00",
    "oil": "2026-07-06T19:57:57.089833+00:00"
  },
  "prices": {
    "markets": {
      "price": 53321.0,
      "change_pct": 0.26,
      "currency": "USD",
      "as_of": "2026-07-06T19:57:12.179539+00:00"
    },
    "nasdaq": {
      "price": 30029.0,
      "change_pct": 1.6,
      "currency": "USD",
      "as_of": "2026-07-06T19:57:21.710991+00:00"
    },
    "s&p 500": {
      "price": 7599.25,
      "change_pct": 0.94,
      "currency": "USD",
      "as_of": "2026-07-06T19:57:28.003459+00:00"
    },
    "crypto": {
      "price": 63731.26,
      "change_pct": 0.22,
      "currency": "USD",
      "as_of": "2026-07-06T19:57:33.580300+00:00"
    },
    "forex": {
      "price": 1.1444,
      "change_pct": 0.03,
      "currency": "USD",
      "as_of": "2026-07-06T19:57:39.696091+00:00"
    },
    "gold": {
      "price": 4174.5,
      "change_pct": 1.18,
      "currency": "USD",
      "as_of": "2026-07-06T19:57:45.795081+00:00"
    },
    "oil": {
      "price": 68.75,
      "change_pct": 0.09,
      "currency": "USD",
      "as_of": "2026-07-06T19:57:51.259437+00:00"
    }
  },
  "structures": {
    "markets": {
      "price": 53321.0,
      "session": "NY",
      "zone": "premium",
      "trend": "flat",
      "session_trend": "broadly rangebound since the Asia session",
      "momentum": "flat",
      "recent_action": "coiling in a tight, balanced range",
      "range_pct": 82.0,
      "prior_day_high": 53257.0,
      "prior_day_low": 53140.0,
      "pdh_swept": true,
      "pdl_swept": true,
      "today_high": 53382.0,
      "today_low": 52962.0,
      "range_high": 53400.0,
      "range_low": 52962.0,
      "equilibrium": 53181.0,
      "sessions": {
        "Asia": [
          53296.0,
          53148.0
        ],
        "London": [
          53310.0,
          53107.0
        ],
        "NY": [
          53382.0,
          52962.0
        ]
      }
    },
    "nasdaq": {
      "price": 30029.0,
      "session": "NY",
      "zone": "premium",
      "trend": "flat",
      "session_trend": "broadly rangebound since the Asia session",
      "momentum": "up",
      "recent_action": "pushing higher and holding near the highs",
      "range_pct": 88.6,
      "prior_day_high": 30011.25,
      "prior_day_low": 29860.75,
      "pdh_swept": true,
      "pdl_swept": true,
      "today_high": 30094.0,
      "today_low": 29683.0,
      "range_high": 30094.0,
      "range_low": 29522.0,
      "equilibrium": 29808.0,
      "sessions": {
        "Asia": [
          30004.75,
          29683.0
        ],
        "London": [
          29915.0,
          29780.0
        ],
        "NY": [
          30094.0,
          29776.25
        ]
      }
    },
    "s&p 500": {
      "price": 7599.25,
      "session": "NY",
      "zone": "premium",
      "trend": "up",
      "session_trend": "trading higher since the Asia session",
      "momentum": "up",
      "recent_action": "pushing higher and holding near the highs",
      "range_pct": 95.7,
      "prior_day_high": 7570.75,
      "prior_day_low": 7551.5,
      "pdh_swept": true,
      "pdl_swept": true,
      "today_high": 7602.5,
      "today_low": 7538.25,
      "range_high": 7602.5,
      "range_low": 7527.25,
      "equilibrium": 7564.875,
      "sessions": {
        "Asia": [
          7574.25,
          7538.25
        ],
        "London": [
          7566.75,
          7552.5
        ],
        "NY": [
          7602.5,
          7551.75
        ]
      }
    },
    "crypto": {
      "price": 63437.0,
      "session": "NY",
      "zone": "premium",
      "trend": "up",
      "session_trend": "trading higher since the Asia session",
      "momentum": "up",
      "recent_action": "pushing higher and holding near the highs",
      "range_pct": 83.3,
      "prior_day_high": 63383.0,
      "prior_day_low": 62462.0,
      "pdh_swept": true,
      "pdl_swept": true,
      "today_high": 63857.0,
      "today_low": 61339.0,
      "range_high": 63857.0,
      "range_low": 61339.0,
      "equilibrium": 62598.0,
      "sessions": {
        "Asia": [
          63857.0,
          62576.0
        ],
        "London": [
          63286.0,
          62844.0
        ],
        "NY": [
          63437.0,
          61339.0
        ]
      }
    },
    "forex": {
      "price": 1.14443,
      "session": "NY",
      "zone": "equilibrium",
      "trend": "flat",
      "session_trend": "broadly rangebound since the Asia session",
      "momentum": "flat",
      "recent_action": "coiling in a tight, balanced range",
      "range_pct": 60.9,
      "prior_day_high": 1.14416,
      "prior_day_low": 1.14364,
      "pdh_swept": true,
      "pdl_swept": true,
      "today_high": 1.14482,
      "today_low": 1.14116,
      "range_high": 1.14653,
      "range_low": 1.14116,
      "equilibrium": 1.14384,
      "sessions": {
        "Asia": [
          1.14443,
          1.14233
        ],
        "London": [
          1.14312,
          1.14129
        ],
        "NY": [
          1.14482,
          1.14116
        ]
      }
    },
    "gold": {
      "price": 4174.5,
      "session": "NY",
      "zone": "equilibrium",
      "trend": "down",
      "session_trend": "under pressure since the Asia session",
      "momentum": "up",
      "recent_action": "grinding up off the lows",
      "range_pct": 48.5,
      "prior_day_high": 4214.1001,
      "prior_day_low": 4184.3999,
      "pdh_swept": true,
      "pdl_swept": true,
      "today_high": 4215.5,
      "today_low": 4140.6001,
      "range_high": 4215.5,
      "range_low": 4135.8999,
      "equilibrium": 4175.69995,
      "sessions": {
        "Asia": [
          4215.5,
          4156.3999
        ],
        "London": [
          4187.2998,
          4148.3999
        ],
        "NY": [
          4187.2998,
          4140.6001
        ]
      }
    },
    "oil": {
      "price": 68.75,
      "session": "NY",
      "zone": "equilibrium",
      "trend": "up",
      "session_trend": "trading higher since the Asia session",
      "momentum": "up",
      "recent_action": "pushing higher and holding near the highs",
      "range_pct": 66.9,
      "prior_day_high": 68.78,
      "prior_day_low": 68.22,
      "pdh_swept": true,
      "pdl_swept": true,
      "today_high": 69.21,
      "today_low": 67.82,
      "range_high": 69.21,
      "range_low": 67.82,
      "equilibrium": 68.515,
      "sessions": {
        "Asia": [
          69.21,
          68.16
        ],
        "London": [
          68.78,
          67.82
        ],
        "NY": [
          69.12,
          68.07
        ]
      }
    }
  },
  "macro": "MACRO CONTEXT (cross-asset, delayed): US Dollar Index (DXY) flat 0.02%; US 10Y yield down 0.13%; Volatility (VIX) down 1.27%.",
  "calendar": "ECONOMIC CALENDAR (high-impact, upcoming): NZD Official Cash Rate (tomorrow); NZD RBNZ Rate Statement (tomorrow); NZD RBNZ Press Conference (tomorrow); USD FOMC Meeting Minutes (Wed); CAD Employment Change (Fri); CAD Unemployment Rate (Fri).",
  "timing": "TIMING: 15:57 New York time — the New York PM killzone is active right now (a window when smart money commonly seeks liquidity).",
  "sentiment": "SENTIMENT: the Crypto Fear & Greed Index reads 24 (Extreme Fear) — a contrarian gauge of crowd positioning."
}